entmax/__init__.py
entmax/activations.py
entmax/losses.py
entmax/root_finding.py
entmax/test_losses.py
entmax/test_mask.py
entmax/test_root_finding.py
entmax/test_topk.py
entmax-1.2.dist-info/LICENSE
entmax-1.2.dist-info/METADATA
entmax-1.2.dist-info/WHEEL
entmax-1.2.dist-info/top_level.txt
entmax-1.2.dist-info/RECORD
